MANIFEST.in
Makefile
README.rst
__init__.py
setup.cfg
setup.py
stati/__init__.py
stati/client.py
stati/exceptions.py
stati.egg-info/PKG-INFO
stati.egg-info/SOURCES.txt
stati.egg-info/dependency_links.txt
stati.egg-info/requires.txt
stati.egg-info/top_level.txt