Metadata-Version: 1.1
Name: stati
Version: 0.0.2
Summary: Python client for GottWall statistics server
Home-page: https://github.com/GottWall/stati-python
Author: Alexandr Lispython
Author-email: alex@obout.ru
License: BSD
Platform: Linux
Platform: Mac
Classifier: Environment :: Web Environment
Classifier: License :: OSI Approved :: BSD License
Classifier: Programming Language :: Python
Classifier: Operating System :: MacOS :: MacOS X
Classifier: Operating System :: POSIX
Classifier: Topic :: Internet
Classifier: Topic :: Software Development :: Libraries
